GoByExampleZhongwenban/README.md
GoByExampleZhongwenban/__init__.py
GoByExampleZhongwenban/__main__.py
GoByExampleZhongwenban/file.epub
GoByExampleZhongwenban/index.html
GoByExampleZhongwenban/css/__init__.py
GoByExampleZhongwenban/css/annotations.css
GoByExampleZhongwenban/css/main.css
GoByExampleZhongwenban/css/normalize.css
GoByExampleZhongwenban/css/popup.css
GoByExampleZhongwenban/font/__init__.py
GoByExampleZhongwenban/font/fontello.eot
GoByExampleZhongwenban/font/fontello.svg
GoByExampleZhongwenban/font/fontello.ttf
GoByExampleZhongwenban/font/fontello.woff
GoByExampleZhongwenban/img/__init__.py
GoByExampleZhongwenban/img/annotator-glyph-sprite.png
GoByExampleZhongwenban/img/annotator-icon-sprite.png
GoByExampleZhongwenban/img/apple-touch-icon.png
GoByExampleZhongwenban/img/cancelfullscreen.png
GoByExampleZhongwenban/img/close.png
GoByExampleZhongwenban/img/fullscreen.png
GoByExampleZhongwenban/img/loader.gif
GoByExampleZhongwenban/img/menu-icon.png
GoByExampleZhongwenban/img/save.png
GoByExampleZhongwenban/img/saved.png
GoByExampleZhongwenban/img/settings-s.png
GoByExampleZhongwenban/img/settings.png
GoByExampleZhongwenban/img/star.png
GoByExampleZhongwenban/js/__init__.py
GoByExampleZhongwenban/js/epub.js
GoByExampleZhongwenban/js/epub.min.js
GoByExampleZhongwenban/js/epub.min.map
GoByExampleZhongwenban/js/hooks.min.js
GoByExampleZhongwenban/js/hooks.min.map
GoByExampleZhongwenban/js/reader.js
GoByExampleZhongwenban/js/reader.js.map
GoByExampleZhongwenban/js/reader.min.js
GoByExampleZhongwenban/js/reader.min.map
GoByExampleZhongwenban/js/hooks/__init__.py
GoByExampleZhongwenban/js/hooks/extensions/__init__.py
GoByExampleZhongwenban/js/hooks/extensions/highlight.js
GoByExampleZhongwenban/js/libs/__init__.py
GoByExampleZhongwenban/js/libs/jquery.min.js
GoByExampleZhongwenban/js/libs/localforage.min.js
GoByExampleZhongwenban/js/libs/screenfull.js
GoByExampleZhongwenban/js/libs/screenfull.min.js
GoByExampleZhongwenban/js/libs/zip.min.js
go_by_example_zhongwenban-2024.3.2.0.dist-info/METADATA
go_by_example_zhongwenban-2024.3.2.0.dist-info/WHEEL
go_by_example_zhongwenban-2024.3.2.0.dist-info/entry_points.txt
go_by_example_zhongwenban-2024.3.2.0.dist-info/top_level.txt
go_by_example_zhongwenban-2024.3.2.0.dist-info/RECORD
